package com.liuyuncen.juc.locks;

public class LockSyncDemo {

    Object object = new Object();

    public void m1(){
        synchronized (object){
            System.out.println("--- hello");
        }
    }
    public static void main(String[] args) {

    }
}

/*

  public void m1();
    descriptor: ()V
    flags: ACC_PUBLIC
    Code:
      stack=2, locals=3, args_size=1
         0: aload_0
         1: getfield      #3                  // Field object:Ljava/lang/Object;
         4: dup
         5: astore_1
         6: monitorenter
         7: getstatic     #4                  // Field java/lang/System.out:Ljava/io/PrintStream;
        10: ldc           #5                  // String --- hello
        12: invokevirtual #6                  // Method java/io/PrintStream.println:(Ljava/lang/String;)V
        15: aload_1
        16: monitorexit
        17: goto          25
        20: astore_2
        21: aload_1
        22: monitorexit
        23: aload_2
        24: athrow
        25: return
      Exception table:

 */
